<?xml version="1.0" encoding="utf-8" ?>
<dwsync>
<file name="_common.php" server="hgp2020.cafe24.com//www/" local="132591201825273487" remote="132284988000000000" Dst="0" />
<file name="_head.php" server="hgp2020.cafe24.com//www/" local="132591201825283467" remote="132284988000000000" Dst="0" />
<file name="_head.sub.php" server="hgp2020.cafe24.com//www/" local="132591201825572685" remote="132284988000000000" Dst="0" />
<file name="_tail.php" server="hgp2020.cafe24.com//www/" local="132591201826001546" remote="132284988000000000" Dst="0" />
<file name="_tail.sub.php" server="hgp2020.cafe24.com//www/" local="132591201826101279" remote="132284988000000000" Dst="0" />
<file name="ajax.autosave.php" server="hgp2020.cafe24.com//www/" local="132591201826131191" remote="132284988000000000" Dst="0" />
<file name="ajax.autosavedel.php" server="hgp2020.cafe24.com//www/" local="132591201826460322" remote="132284988000000000" Dst="0" />
<file name="ajax.autosavelist.php" server="hgp2020.cafe24.com//www/" local="132591201826490248" remote="132284988000000000" Dst="0" />
<file name="ajax.autosaveload.php" server="hgp2020.cafe24.com//www/" local="132591201826570018" remote="132284988000000000" Dst="0" />
<file name="ajax.comment_token.php" server="hgp2020.cafe24.com//www/" local="132591201826589971" remote="132284988000000000" Dst="0" />
<file name="ajax.filter.php" server="hgp2020.cafe24.com//www/" local="132591201826919097" remote="132284988000000000" Dst="0" />
<file name="ajax.mb_email.php" server="hgp2020.cafe24.com//www/" local="132591201826949015" remote="132284988000000000" Dst="0" />
<file name="ajax.mb_hp.php" server="hgp2020.cafe24.com//www/" local="132591201827028806" remote="132284988000000000" Dst="0" />
<file name="ajax.mb_id.php" server="hgp2020.cafe24.com//www/" local="132591201827078921" remote="132284988000000000" Dst="0" />
<file name="ajax.mb_nick.php" server="hgp2020.cafe24.com//www/" local="132591201827367900" remote="132284988000000000" Dst="0" />
<file name="ajax.mb_recommend.php" server="hgp2020.cafe24.com//www/" local="132591201827467631" remote="132284988000000000" Dst="0" />
<file name="alert.php" server="hgp2020.cafe24.com//www/" local="132591201827507514" remote="132284988000000000" Dst="0" />
<file name="alert_close.php" server="hgp2020.cafe24.com//www/" local="132591201827826664" remote="132284988000000000" Dst="0" />
<file name="board.php" server="hgp2020.cafe24.com//www/" local="132591201827866553" remote="132284988000000000" Dst="0" />
<file name="board_head.php" server="hgp2020.cafe24.com//www/" local="132591201828385168" remote="132284988000000000" Dst="0" />
<file name="board_list_update.php" server="hgp2020.cafe24.com//www/" local="132591201828405116" remote="132284988000000000" Dst="0" />
<file name="board_tail.php" server="hgp2020.cafe24.com//www/" local="132591201828435049" remote="132284988000000000" Dst="0" />
<file name="confirm.php" server="hgp2020.cafe24.com//www/" local="132591201828504849" remote="132284988000000000" Dst="0" />
<file name="content.php" server="hgp2020.cafe24.com//www/" local="132591201828524799" remote="132284988000000000" Dst="0" />
<file name="current_connect.php" server="hgp2020.cafe24.com//www/" local="132591201828554714" remote="132284988000000000" Dst="0" />
<file name="db_table.optimize.php" server="hgp2020.cafe24.com//www/" local="132591201828854164" remote="132284988000000000" Dst="0" />
<file name="delete.php" server="hgp2020.cafe24.com//www/" local="132591201828893807" remote="132284988000000000" Dst="0" />
<file name="delete_all.php" server="hgp2020.cafe24.com//www/" local="132591201829332640" remote="132284988000000000" Dst="0" />
<file name="delete_comment.php" server="hgp2020.cafe24.com//www/" local="132591201829352598" remote="132284988000000000" Dst="0" />
<file name="download.php" server="hgp2020.cafe24.com//www/" local="132591201829362572" remote="132284988000000000" Dst="0" />
<file name="email_certify.php" server="hgp2020.cafe24.com//www/" local="132591201829771470" remote="132284988000000000" Dst="0" />
<file name="email_stop.php" server="hgp2020.cafe24.com//www/" local="132591201829791420" remote="132284988000000000" Dst="0" />
<file name="faq.php" server="hgp2020.cafe24.com//www/" local="132591201829801380" remote="132284988000000000" Dst="0" />
<file name="formmail.php" server="hgp2020.cafe24.com//www/" local="132591201830220271" remote="132284988000000000" Dst="0" />
<file name="formmail_send.php" server="hgp2020.cafe24.com//www/" local="132591201830250197" remote="132284988000000000" Dst="0" />
<file name="good.php" server="hgp2020.cafe24.com//www/" local="132591201830270150" remote="132284988000000000" Dst="0" />
<file name="group.php" server="hgp2020.cafe24.com//www/" local="132591201830509487" remote="132284988000000000" Dst="0" />
<file name="link.php" server="hgp2020.cafe24.com//www/" local="132591201830569333" remote="132284988000000000" Dst="0" />
<file name="login.php" server="hgp2020.cafe24.com//www/" local="132591201830978236" remote="132284988000000000" Dst="0" />
<file name="list.php" server="hgp2020.cafe24.com//www/" local="132591201830998196" remote="132284988000000000" Dst="0" />
<file name="login_check.php" server="hgp2020.cafe24.com//www/" local="132591201831018139" remote="132284988000000000" Dst="0" />
<file name="logout.php" server="hgp2020.cafe24.com//www/" local="132591201831117870" remote="132284988000000000" Dst="0" />
<file name="member_confirm.php" server="hgp2020.cafe24.com//www/" local="132591201831137811" remote="132284988000000000" Dst="0" />
<file name="member_leave.php" server="hgp2020.cafe24.com//www/" local="132591201831407089" remote="132284988000000000" Dst="0" />
<file name="memo.php" server="hgp2020.cafe24.com//www/" local="132591201831437023" remote="132284988000000000" Dst="0" />
<file name="memo_delete.php" server="hgp2020.cafe24.com//www/" local="132591201831706292" remote="132284988000000000" Dst="0" />
<file name="memo_form.php" server="hgp2020.cafe24.com//www/" local="132591201831726243" remote="132284988000000000" Dst="0" />
<file name="memo_form_update.php" server="hgp2020.cafe24.com//www/" local="132591201831865876" remote="132284988000000000" Dst="0" />
<file name="memo_view.php" server="hgp2020.cafe24.com//www/" local="132591201831875837" remote="132284988000000000" Dst="0" />
<file name="move.php" server="hgp2020.cafe24.com//www/" local="132591201832175039" remote="132284988000000000" Dst="0" />
<file name="move_update.php" server="hgp2020.cafe24.com//www/" local="132591201832204959" remote="132284988000000000" Dst="0" />
<file name="new.php" server="hgp2020.cafe24.com//www/" local="132591201832823307" remote="132284988000000000" Dst="0" />
<file name="new_delete.php" server="hgp2020.cafe24.com//www/" local="132591201832873174" remote="132284988000000000" Dst="0" />
<file name="newwin.inc.php" server="hgp2020.cafe24.com//www/" local="132591201832903091" remote="132284988000000000" Dst="0" />
<file name="password.php" server="hgp2020.cafe24.com//www/" local="132591201832952966" remote="132284988000000000" Dst="0" />
<file name="password_check.php" server="hgp2020.cafe24.com//www/" local="132591201833012801" remote="132284988000000000" Dst="0" />
<file name="password_lost.php" server="hgp2020.cafe24.com//www/" local="132591201833361863" remote="132284988000000000" Dst="0" />
<file name="password_lost2.php" server="hgp2020.cafe24.com//www/" local="132591201833401761" remote="132284988000000000" Dst="0" />
<file name="password_lost_certify.php" server="hgp2020.cafe24.com//www/" local="132591201833810668" remote="132284988000000000" Dst="0" />
<file name="point.php" server="hgp2020.cafe24.com//www/" local="132591201833830614" remote="132284988000000000" Dst="0" />
<file name="poll_etc_update.php" server="hgp2020.cafe24.com//www/" local="132591201834269441" remote="132284988000000000" Dst="0" />
<file name="poll_etc_update_mail.php" server="hgp2020.cafe24.com//www/" local="132591201834279425" remote="132284988000000000" Dst="0" />
<file name="poll_result.php" server="hgp2020.cafe24.com//www/" local="132591201834399107" remote="132284988000000000" Dst="0" />
<file name="poll_update.php" server="hgp2020.cafe24.com//www/" local="132591201834429031" remote="132284988000000000" Dst="0" />
<file name="profile.php" server="hgp2020.cafe24.com//www/" local="132591201834857088" remote="132284988000000000" Dst="0" />
<file name="qadelete.php" server="hgp2020.cafe24.com//www/" local="132591201834877067" remote="132284988000000000" Dst="0" />
<file name="qahead.php" server="hgp2020.cafe24.com//www/" local="132591201835166254" remote="132284988000000000" Dst="0" />
<file name="qadownload.php" server="hgp2020.cafe24.com//www/" local="132591201835186206" remote="132284988000000000" Dst="0" />
<file name="qalist.php" server="hgp2020.cafe24.com//www/" local="132591201835615060" remote="132284988000000000" Dst="0" />
<file name="qatail.php" server="hgp2020.cafe24.com//www/" local="132591201835635019" remote="132284988000000000" Dst="0" />
<file name="qaview.php" server="hgp2020.cafe24.com//www/" local="132591201835924241" remote="132284988000000000" Dst="0" />
<file name="qawrite.php" server="hgp2020.cafe24.com//www/" local="132591201835944175" remote="132284988000000000" Dst="0" />
<file name="register.php" server="hgp2020.cafe24.com//www/" local="132591201836053885" remote="132284988000000000" Dst="0" />
<file name="qawrite_update.php" server="hgp2020.cafe24.com//www/" local="132591201836073829" remote="132284988000000000" Dst="0" />
<file name="register_email.php" server="hgp2020.cafe24.com//www/" local="132591201836353088" remote="132284988000000000" Dst="0" />
<file name="register_email_update.php" server="hgp2020.cafe24.com//www/" local="132591201836462795" remote="132284988000000000" Dst="0" />
<file name="register_form.php" server="hgp2020.cafe24.com//www/" local="132591201836502683" remote="132284988000000000" Dst="0" />
<file name="register_form_update_mail1.php" server="hgp2020.cafe24.com//www/" local="132591201836831805" remote="132284988000000000" Dst="0" />
<file name="register_form_update.php" server="hgp2020.cafe24.com//www/" local="132591201836851751" remote="132284988000000000" Dst="0" />
<file name="register_form_update_mail2.php" server="hgp2020.cafe24.com//www/" local="132591201837011333" remote="132284988000000000" Dst="0" />
<file name="register_form_update_mail3.php" server="hgp2020.cafe24.com//www/" local="132591201837071163" remote="132284988000000000" Dst="0" />
<file name="register_result.php" server="hgp2020.cafe24.com//www/" local="132591201837150954" remote="132284988000000000" Dst="0" />
<file name="rss.php" server="hgp2020.cafe24.com//www/" local="132591201837160941" remote="132284988000000000" Dst="0" />
<file name="scrap.php" server="hgp2020.cafe24.com//www/" local="132591201837400285" remote="132284988000000000" Dst="0" />
<file name="scrap_delete.php" server="hgp2020.cafe24.com//www/" local="132591201837430203" remote="132284988000000000" Dst="0" />
<file name="scrap_popin.php" server="hgp2020.cafe24.com//www/" local="132591201837669592" remote="132284988000000000" Dst="0" />
<file name="scrap_popin_update.php" server="hgp2020.cafe24.com//www/" local="132591201837689592" remote="132284988000000000" Dst="0" />
<file name="search.php" server="hgp2020.cafe24.com//www/" local="132591201837719459" remote="132284988000000000" Dst="0" />
<file name="sns_send.php" server="hgp2020.cafe24.com//www/" local="132591201837769299" remote="132284988000000000" Dst="0" />
<file name="view.php" server="hgp2020.cafe24.com//www/" local="132591201838277938" remote="132284988000000000" Dst="0" />
<file name="view_comment.php" server="hgp2020.cafe24.com//www/" local="132591201838297883" remote="132284988000000000" Dst="0" />
<file name="view_image.php" server="hgp2020.cafe24.com//www/" local="132591201838317845" remote="132284988000000000" Dst="0" />
<file name="visit_browscap.inc.php" server="hgp2020.cafe24.com//www/" local="132591201838377678" remote="132284988000000000" Dst="0" />
<file name="visit_insert.inc.php" server="hgp2020.cafe24.com//www/" local="132591201838746693" remote="132284988000000000" Dst="0" />
<file name="write_comment_update.php" server="hgp2020.cafe24.com//www/" local="132591201838806526" remote="132284988000000000" Dst="0" />
<file name="write.php" server="hgp2020.cafe24.com//www/" local="132591201838826488" remote="132284988000000000" Dst="0" />
<file name="write_comment_update.sns.php" server="hgp2020.cafe24.com//www/" local="132591201839225412" remote="132284988000000000" Dst="0" />
<file name="write_token.php" server="hgp2020.cafe24.com//www/" local="132591201839255332" remote="132284988000000000" Dst="0" />
<file name="write_update.php" server="hgp2020.cafe24.com//www/" local="132591201839414917" remote="132284988000000000" Dst="0" />
<file name="write_update_mail.php" server="hgp2020.cafe24.com//www/" local="132591201839464768" remote="132284988000000000" Dst="0" />
</dwsync>